{
  "n": 150,
  "sample": 150,
  "seen": 1050,
  "every": 7,
  "budget_lo": 200,
  "budget_hi": 2000,
  "gap_median": 0.0,
  "gap_mean": 0.045,
  "gap_p90": 0.0,
  "gap_max": 12.8,
  "pct_positive": 2.0,
  "pct_significant": 2.0,
  "greedy_lo": 12,
  "greedy_hi": 12,
  "greedy_lo_only": 0,
  "pct_greedy_lo": 8.0,
  "by_bag": {
    "6": {
      "n": 6,
      "sig": 1,
      "greedy": 0,
      "gapsum": 2.0
    },
    "7": {
      "n": 3,
      "sig": 0,
      "greedy": 0,
      "gapsum": 0.0
    },
    "4": {
      "n": 26,
      "sig": 0,
      "greedy": 1,
      "gapsum": 0.0
    },
    "3": {
      "n": 107,
      "sig": 1,
      "greedy": 9,
      "gapsum": 1.5999999999999943
    },
    "5": {
      "n": 8,
      "sig": 1,
      "greedy": 2,
      "gapsum": 3.200000000000003
    }
  },
  "rows": [
    {
      "order_id": "474405",
      "bag": 6,
      "makespan_200": 122.3,
      "makespan_hi": 120.3,
      "gap_min": 2.0,
      "strat_200": "ortools",
      "strat_hi": "ortools",
      "greedy_200": false,
      "greedy_hi": false,
      "significant": true
    },
    {
      "order_id": "474412",
      "bag": 7,
      "makespan_200": 111.3,
      "makespan_hi": 111.3,
      "gap_min": 0.0,
      "strat_200": "ortools",
      "strat_hi": "ortools",
      "greedy_200": false,
      "greedy_hi": false,
      "significant": false
    },
    {
      "order_id": "474419",
      "bag": 7,
      "makespan_200": 109.4,
      "makespan_hi": 109.4,
      "gap_min": 0.0,
      "strat_200": "ortools",
      "strat_hi": "ortools",
      "greedy_200": false,
      "greedy_hi": false,
      "significant": false
    },
    {
      "order_id": "474422",
      "bag": 4,
      "makespan_200": 72.0,
      "makespan_hi": 72.0,
      "gap_min": 0.0,
      "strat_200": "ortools",
      "strat_hi": "ortools",
      "greedy_200": false,
      "greedy_hi": false,
      "significant": false
    },
    {
      "order_id": "474418",
      "bag": 4,
      "makespan_200": 62.0,
      "makespan_hi": 62.0,
      "gap_min": 0.0,
      "strat_200": "ortools",
      "strat_hi": "ortools",
      "greedy_200": false,
      "greedy_hi": false,
      "significant": false
    },
    {
      "order_id": "474418",
      "bag": 4,
      "makespan_200": 56.8,
      "makespan_hi": 56.8,
      "gap_min": 0.0,
      "strat_200": "ortools",
      "strat_hi": "ortools",
      "greedy_200": false,
      "greedy_hi": false,
      "significant": false
    },
    {
      "order_id": "474429",
      "bag": 3,
      "makespan_200": 50.6,
      "makespan_hi": 50.6,
      "gap_min": 0.0,
      "strat_200": "ortools",
      "strat_hi": "ortools",
      "greedy_200": false,
      "greedy_hi": false,
      "significant": false
    },
    {
      "order_id": "474431",
      "bag": 3,
      "makespan_200": 46.4,
      "makespan_hi": 46.4,
      "gap_min": 0.0,
      "strat_200": "ortools",
      "strat_hi": "ortools",
      "greedy_200": false,
      "greedy_hi": false,
      "significant": false
    },
    {
      "order_id": "474433",
      "bag": 5,
      "makespan_200": 71.5,
      "makespan_hi": 68.3,
      "gap_min": 3.2,
      "strat_200": "ortools",
      "strat_hi": "ortools",
      "greedy_200": false,
      "greedy_hi": false,
      "significant": true
    },
    {
      "order_id": "474437",
      "bag": 7,
      "makespan_200": 113.0,
      "makespan_hi": 113.0,
      "gap_min": 0.0,
      "strat_200": "ortools",
      "strat_hi": "ortools",
      "greedy_200": false,
      "greedy_hi": false,
      "significant": false
    },
    {
      "order_id": "474442",
      "bag": 6,
      "makespan_200": 99.0,
      "makespan_hi": 99.0,
      "gap_min": 0.0,
      "strat_200": "ortools",
      "strat_hi": "ortools",
      "greedy_200": false,
      "greedy_hi": false,
      "significant": false
    },
    {
      "order_id": "474444",
      "bag": 6,
      "makespan_200": 57.6,
      "makespan_hi": 57.6,
      "gap_min": 0.0,
      "strat_200": "ortools",
      "strat_hi": "ortools",
      "greedy_200": false,
      "greedy_hi": false,
      "significant": false
    },
    {
      "order_id": "474447",
      "bag": 3,
      "makespan_200": 47.2,
      "makespan_hi": 47.2,
      "gap_min": 0.0,
      "strat_200": "ortools",
      "strat_hi": "ortools",
      "greedy_200": false,
      "greedy_hi": false,
      "significant": false
    },
    {
      "order_id": "474451",
      "bag": 3,
      "makespan_200": 48.0,
      "makespan_hi": 48.0,
      "gap_min": 0.0,
      "strat_200": "ortools",
      "strat_hi": "ortools",
      "greedy_200": false,
      "greedy_hi": false,
      "significant": false
    },
    {
      "order_id": "474453",
      "bag": 3,
      "makespan_200": 58.5,
      "makespan_hi": 58.5,
      "gap_min": 0.0,
      "strat_200": "ortools",
      "strat_hi": "ortools",
      "greedy_200": false,
      "greedy_hi": false,
      "significant": false
    },
    {
      "order_id": "474454",
      "bag": 3,
      "makespan_200": 51.2,
      "makespan_hi": 51.2,
      "gap_min": 0.0,
      "strat_200": "ortools",
      "strat_hi": "ortools",
      "greedy_200": false,
      "greedy_hi": false,
      "significant": false
    },
    {
      "order_id": "474461",
      "bag": 3,
      "makespan_200": 55.7,
      "makespan_hi": 55.7,
      "gap_min": 0.0,
      "strat_200": "ortools",
      "strat_hi": "ortools",
      "greedy_200": false,
      "greedy_hi": false,
      "significant": false
    },
    {
      "order_id": "474466",
      "bag": 3,
      "makespan_200": 52.3,
      "makespan_hi": 52.3,
      "gap_min": 0.0,
      "strat_200": "ortools",
      "strat_hi": "ortools",
      "greedy_200": false,
      "greedy_hi": false,
      "significant": false
    },
    {
      "order_id": "474475",
      "bag": 3,
      "makespan_200": 62.5,
      "makespan_hi": 62.5,
      "gap_min": 0.0,
      "strat_200": "ortools",
      "strat_hi": "ortools",
      "greedy_200": false,
      "greedy_hi": false,
      "significant": false
    },
    {
      "order_id": "474484",
      "bag": 5,
      "makespan_200": 20087.8,
      "makespan_hi": 20087.8,
      "gap_min": 0.0,
      "strat_200": "greedy_fallback",
      "strat_hi": "greedy_fallback",
      "greedy_200": true,
      "greedy_hi": true,
      "significant": false
    },
    {
      "order_id": "474490",
      "bag": 3,
      "makespan_200": 20049.9,
      "makespan_hi": 20049.9,
      "gap_min": 0.0,
      "strat_200": "greedy_fallback",
      "strat_hi": "greedy_fallback",
      "greedy_200": true,
      "greedy_hi": true,
      "significant": false
    },
    {
      "order_id": "474493",
      "bag": 3,
      "makespan_200": 20059.7,
      "makespan_hi": 20059.7,
      "gap_min": 0.0,
      "strat_200": "greedy_fallback",
      "strat_hi": "greedy_fallback",
      "greedy_200": true,
      "greedy_hi": true,
      "significant": false
    },
    {
      "order_id": "474508",
      "bag": 3,
      "makespan_200": 68.7,
      "makespan_hi": 68.7,
      "gap_min": 0.0,
      "strat_200": "ortools",
      "strat_hi": "ortools",
      "greedy_200": false,
      "greedy_hi": false,
      "significant": false
    },
    {
      "order_id": "474500",
      "bag": 3,
      "makespan_200": 66.6,
      "makespan_hi": 66.6,
      "gap_min": 0.0,
      "strat_200": "ortools",
      "strat_hi": "ortools",
      "greedy_200": false,
      "greedy_hi": false,
      "significant": false
    },
    {
      "order_id": "474519",
      "bag": 3,
      "makespan_200": 56.7,
      "makespan_hi": 56.7,
      "gap_min": 0.0,
      "strat_200": "ortools",
      "strat_hi": "ortools",
      "greedy_200": false,
      "greedy_hi": false,
      "significant": false
    },
    {
      "order_id": "474531",
      "bag": 3,
      "makespan_200": 67.4,
      "makespan_hi": 67.4,
      "gap_min": 0.0,
      "strat_200": "ortools",
      "strat_hi": "ortools",
      "greedy_200": false,
      "greedy_hi": false,
      "significant": false
    },
    {
      "order_id": "474537",
      "bag": 3,
      "makespan_200": 62.3,
      "makespan_hi": 62.3,
      "gap_min": 0.0,
      "strat_200": "ortools",
      "strat_hi": "ortools",
      "greedy_200": false,
      "greedy_hi": false,
      "significant": false
    },
    {
      "order_id": "474539",
      "bag": 3,
      "makespan_200": 51.4,
      "makespan_hi": 51.4,
      "gap_min": 0.0,
      "strat_200": "ortools",
      "strat_hi": "ortools",
      "greedy_200": false,
      "greedy_hi": false,
      "significant": false
    },
    {
      "order_id": "474544",
      "bag": 3,
      "makespan_200": 63.2,
      "makespan_hi": 63.2,
      "gap_min": 0.0,
      "strat_200": "ortools",
      "strat_hi": "ortools",
      "greedy_200": false,
      "greedy_hi": false,
      "significant": false
    },
    {
      "order_id": "474546",
      "bag": 3,
      "makespan_200": 72.0,
      "makespan_hi": 72.0,
      "gap_min": 0.0,
      "strat_200": "ortools",
      "strat_hi": "ortools",
      "greedy_200": false,
      "greedy_hi": false,
      "significant": false
    },
    {
      "order_id": "474550",
      "bag": 3,
      "makespan_200": 68.9,
      "makespan_hi": 68.9,
      "gap_min": 0.0,
      "strat_200": "ortools",
      "strat_hi": "ortools",
      "greedy_200": false,
      "greedy_hi": false,
      "significant": false
    },
    {
      "order_id": "474553",
      "bag": 3,
      "makespan_200": 60.0,
      "makespan_hi": 60.0,
      "gap_min": 0.0,
      "strat_200": "ortools",
      "strat_hi": "ortools",
      "greedy_200": false,
      "greedy_hi": false,
      "significant": false
    },
    {
      "order_id": "474555",
      "bag": 3,
      "makespan_200": 70.2,
      "makespan_hi": 70.2,
      "gap_min": 0.0,
      "strat_200": "ortools",
      "strat_hi": "ortools",
      "greedy_200": false,
      "greedy_hi": false,
      "significant": false
    },
    {
      "order_id": "474557",
      "bag": 3,
      "makespan_200": 55.2,
      "makespan_hi": 55.2,
      "gap_min": 0.0,
      "strat_200": "ortools",
      "strat_hi": "ortools",
      "greedy_200": false,
      "greedy_hi": false,
      "significant": false
    },
    {
      "order_id": "474560",
      "bag": 3,
      "makespan_200": 20051.2,
      "makespan_hi": 20051.2,
      "gap_min": 0.0,
      "strat_200": "greedy_fallback",
      "strat_hi": "greedy_fallback",
      "greedy_200": true,
      "greedy_hi": true,
      "significant": false
    },
    {
      "order_id": "474564",
      "bag": 3,
      "makespan_200": 48.9,
      "makespan_hi": 48.9,
      "gap_min": 0.0,
      "strat_200": "ortools",
      "strat_hi": "ortools",
      "greedy_200": false,
      "greedy_hi": false,
      "significant": false
    },
    {
      "order_id": "474573",
      "bag": 5,
      "makespan_200": 82.7,
      "makespan_hi": 82.7,
      "gap_min": 0.0,
      "strat_200": "ortools",
      "strat_hi": "ortools",
      "greedy_200": false,
      "greedy_hi": false,
      "significant": false
    },
    {
      "order_id": "474579",
      "bag": 3,
      "makespan_200": 108.4,
      "makespan_hi": 108.4,
      "gap_min": 0.0,
      "strat_200": "ortools",
      "strat_hi": "ortools",
      "greedy_200": false,
      "greedy_hi": false,
      "significant": false
    },
    {
      "order_id": "474580",
      "bag": 3,
      "makespan_200": 42.5,
      "makespan_hi": 42.5,
      "gap_min": 0.0,
      "strat_200": "ortools",
      "strat_hi": "ortools",
      "greedy_200": false,
      "greedy_hi": false,
      "significant": false
    },
    {
      "order_id": "474577",
      "bag": 3,
      "makespan_200": 52.0,
      "makespan_hi": 52.0,
      "gap_min": 0.0,
      "strat_200": "ortools",
      "strat_hi": "ortools",
      "greedy_200": false,
      "greedy_hi": false,
      "significant": false
    },
    {
      "order_id": "474595",
      "bag": 3,
      "makespan_200": 30045.0,
      "makespan_hi": 30045.0,
      "gap_min": 0.0,
      "strat_200": "greedy_fallback",
      "strat_hi": "greedy_fallback",
      "greedy_200": true,
      "greedy_hi": true,
      "significant": false
    },
    {
      "order_id": "474599",
      "bag": 3,
      "makespan_200": 56.4,
      "makespan_hi": 56.4,
      "gap_min": 0.0,
      "strat_200": "ortools",
      "strat_hi": "ortools",
      "greedy_200": false,
      "greedy_hi": false,
      "significant": false
    },
    {
      "order_id": "474601",
      "bag": 3,
      "makespan_200": 54.2,
      "makespan_hi": 54.2,
      "gap_min": 0.0,
      "strat_200": "ortools",
      "strat_hi": "ortools",
      "greedy_200": false,
      "greedy_hi": false,
      "significant": false
    },
    {
      "order_id": "474603",
      "bag": 3,
      "makespan_200": 44.4,
      "makespan_hi": 44.4,
      "gap_min": 0.0,
      "strat_200": "ortools",
      "strat_hi": "ortools",
      "greedy_200": false,
      "greedy_hi": false,
      "significant": false
    },
    {
      "order_id": "474605",
      "bag": 3,
      "makespan_200": 50.8,
      "makespan_hi": 50.8,
      "gap_min": 0.0,
      "strat_200": "ortools",
      "strat_hi": "ortools",
      "greedy_200": false,
      "greedy_hi": false,
      "significant": false
    },
    {
      "order_id": "474607",
      "bag": 3,
      "makespan_200": 73.7,
      "makespan_hi": 73.7,
      "gap_min": 0.0,
      "strat_200": "ortools",
      "strat_hi": "ortools",
      "greedy_200": false,
      "greedy_hi": false,
      "significant": false
    },
    {
      "order_id": "474608",
      "bag": 3,
      "makespan_200": 44.8,
      "makespan_hi": 44.8,
      "gap_min": 0.0,
      "strat_200": "ortools",
      "strat_hi": "ortools",
      "greedy_200": false,
      "greedy_hi": false,
      "significant": false
    },
    {
      "order_id": "474610",
      "bag": 4,
      "makespan_200": 55.6,
      "makespan_hi": 55.6,
      "gap_min": 0.0,
      "strat_200": "ortools",
      "strat_hi": "ortools",
      "greedy_200": false,
      "greedy_hi": false,
      "significant": false
    },
    {
      "order_id": "474613",
      "bag": 3,
      "makespan_200": 67.1,
      "makespan_hi": 67.1,
      "gap_min": 0.0,
      "strat_200": "ortools",
      "strat_hi": "ortools",
      "greedy_200": false,
      "greedy_hi": false,
      "significant": false
    },
    {
      "order_id": "474614",
      "bag": 3,
      "makespan_200": 51.0,
      "makespan_hi": 51.0,
      "gap_min": 0.0,
      "strat_200": "ortools",
      "strat_hi": "ortools",
      "greedy_200": false,
      "greedy_hi": false,
      "significant": false
    },
    {
      "order_id": "474617",
      "bag": 5,
      "makespan_200": 20047.8,
      "makespan_hi": 20047.8,
      "gap_min": 0.0,
      "strat_200": "greedy_fallback",
      "strat_hi": "greedy_fallback",
      "greedy_200": true,
      "greedy_hi": true,
      "significant": false
    },
    {
      "order_id": "474620",
      "bag": 3,
      "makespan_200": 49.7,
      "makespan_hi": 49.7,
      "gap_min": 0.0,
      "strat_200": "ortools",
      "strat_hi": "ortools",
      "greedy_200": false,
      "greedy_hi": false,
      "significant": false
    },
    {
      "order_id": "474622",
      "bag": 3,
      "makespan_200": 58.6,
      "makespan_hi": 58.6,
      "gap_min": 0.0,
      "strat_200": "ortools",
      "strat_hi": "ortools",
      "greedy_200": false,
      "greedy_hi": false,
      "significant": false
    },
    {
      "order_id": "474624",
      "bag": 3,
      "makespan_200": 51.3,
      "makespan_hi": 51.3,
      "gap_min": 0.0,
      "strat_200": "ortools",
      "strat_hi": "ortools",
      "greedy_200": false,
      "greedy_hi": false,
      "significant": false
    },
    {
      "order_id": "474625",
      "bag": 3,
      "makespan_200": 65.6,
      "makespan_hi": 65.6,
      "gap_min": 0.0,
      "strat_200": "ortools",
      "strat_hi": "ortools",
      "greedy_200": false,
      "greedy_hi": false,
      "significant": false
    },
    {
      "order_id": "474627",
      "bag": 3,
      "makespan_200": 47.8,
      "makespan_hi": 47.8,
      "gap_min": 0.0,
      "strat_200": "ortools",
      "strat_hi": "ortools",
      "greedy_200": false,
      "greedy_hi": false,
      "significant": false
    },
    {
      "order_id": "474628",
      "bag": 3,
      "makespan_200": 45.5,
      "makespan_hi": 45.5,
      "gap_min": 0.0,
      "strat_200": "ortools",
      "strat_hi": "ortools",
      "greedy_200": false,
      "greedy_hi": false,
      "significant": false
    },
    {
      "order_id": "474630",
      "bag": 3,
      "makespan_200": 63.6,
      "makespan_hi": 63.6,
      "gap_min": 0.0,
      "strat_200": "ortools",
      "strat_hi": "ortools",
      "greedy_200": false,
      "greedy_hi": false,
      "significant": false
    },
    {
      "order_id": "474633",
      "bag": 4,
      "makespan_200": 52.7,
      "makespan_hi": 52.7,
      "gap_min": 0.0,
      "strat_200": "ortools",
      "strat_hi": "ortools",
      "greedy_200": false,
      "greedy_hi": false,
      "significant": false
    },
    {
      "order_id": "474637",
      "bag": 3,
      "makespan_200": 65.0,
      "makespan_hi": 65.0,
      "gap_min": 0.0,
      "strat_200": "ortools",
      "strat_hi": "ortools",
      "greedy_200": false,
      "greedy_hi": false,
      "significant": false
    },
    {
      "order_id": "474640",
      "bag": 3,
      "makespan_200": 60.5,
      "makespan_hi": 60.5,
      "gap_min": 0.0,
      "strat_200": "ortools",
      "strat_hi": "ortools",
      "greedy_200": false,
      "greedy_hi": false,
      "significant": false
    },
    {
      "order_id": "474645",
      "bag": 3,
      "makespan_200": 68.0,
      "makespan_hi": 68.0,
      "gap_min": 0.0,
      "strat_200": "ortools",
      "strat_hi": "ortools",
      "greedy_200": false,
      "greedy_hi": false,
      "significant": false
    },
    {
      "order_id": "474647",
      "bag": 3,
      "makespan_200": 74.5,
      "makespan_hi": 74.5,
      "gap_min": 0.0,
      "strat_200": "ortools",
      "strat_hi": "ortools",
      "greedy_200": false,
      "greedy_hi": false,
      "significant": false
    },
    {
      "order_id": "474651",
      "bag": 3,
      "makespan_200": 94.8,
      "makespan_hi": 98.3,
      "gap_min": -3.5,
      "strat_200": "ortools",
      "strat_hi": "ortools",
      "greedy_200": false,
      "greedy_hi": false,
      "significant": false
    },
    {
      "order_id": "474652",
      "bag": 3,
      "makespan_200": 70.6,
      "makespan_hi": 70.6,
      "gap_min": 0.0,
      "strat_200": "ortools",
      "strat_hi": "ortools",
      "greedy_200": false,
      "greedy_hi": false,
      "significant": false
    },
    {
      "order_id": "474657",
      "bag": 3,
      "makespan_200": 75.6,
      "makespan_hi": 75.6,
      "gap_min": 0.0,
      "strat_200": "ortools",
      "strat_hi": "ortools",
      "greedy_200": false,
      "greedy_hi": false,
      "significant": false
    },
    {
      "order_id": "474661",
      "bag": 4,
      "makespan_200": 85.3,
      "makespan_hi": 85.3,
      "gap_min": 0.0,
      "strat_200": "ortools",
      "strat_hi": "ortools",
      "greedy_200": false,
      "greedy_hi": false,
      "significant": false
    },
    {
      "order_id": "474663",
      "bag": 3,
      "makespan_200": 72.8,
      "makespan_hi": 72.8,
      "gap_min": 0.0,
      "strat_200": "ortools",
      "strat_hi": "ortools",
      "greedy_200": false,
      "greedy_hi": false,
      "significant": false
    },
    {
      "order_id": "474667",
      "bag": 3,
      "makespan_200": 72.0,
      "makespan_hi": 72.0,
      "gap_min": 0.0,
      "strat_200": "ortools",
      "strat_hi": "ortools",
      "greedy_200": false,
      "greedy_hi": false,
      "significant": false
    },
    {
      "order_id": "474666",
      "bag": 3,
      "makespan_200": 82.8,
      "makespan_hi": 82.8,
      "gap_min": 0.0,
      "strat_200": "ortools",
      "strat_hi": "ortools",
      "greedy_200": false,
      "greedy_hi": false,
      "significant": false
    },
    {
      "order_id": "474671",
      "bag": 3,
      "makespan_200": 51.5,
      "makespan_hi": 51.5,
      "gap_min": 0.0,
      "strat_200": "ortools",
      "strat_hi": "ortools",
      "greedy_200": false,
      "greedy_hi": false,
      "significant": false
    },
    {
      "order_id": "474674",
      "bag": 6,
      "makespan_200": 81.7,
      "makespan_hi": 81.7,
      "gap_min": 0.0,
      "strat_200": "ortools",
      "strat_hi": "ortools",
      "greedy_200": false,
      "greedy_hi": false,
      "significant": false
    },
    {
      "order_id": "474679",
      "bag": 3,
      "makespan_200": 63.5,
      "makespan_hi": 63.5,
      "gap_min": 0.0,
      "strat_200": "ortools",
      "strat_hi": "ortools",
      "greedy_200": false,
      "greedy_hi": false,
      "significant": false
    },
    {
      "order_id": "474681",
      "bag": 3,
      "makespan_200": 49.1,
      "makespan_hi": 49.1,
      "gap_min": 0.0,
      "strat_200": "ortools",
      "strat_hi": "ortools",
      "greedy_200": false,
      "greedy_hi": false,
      "significant": false
    },
    {
      "order_id": "474683",
      "bag": 3,
      "makespan_200": 52.2,
      "makespan_hi": 52.2,
      "gap_min": 0.0,
      "strat_200": "ortools",
      "strat_hi": "ortools",
      "greedy_200": false,
      "greedy_hi": false,
      "significant": false
    },
    {
      "order_id": "474684",
      "bag": 3,
      "makespan_200": 62.1,
      "makespan_hi": 62.1,
      "gap_min": 0.0,
      "strat_200": "ortools",
      "strat_hi": "ortools",
      "greedy_200": false,
      "greedy_hi": false,
      "significant": false
    },
    {
      "order_id": "474685",
      "bag": 3,
      "makespan_200": 67.9,
      "makespan_hi": 67.9,
      "gap_min": 0.0,
      "strat_200": "ortools",
      "strat_hi": "ortools",
      "greedy_200": false,
      "greedy_hi": false,
      "significant": false
    },
    {
      "order_id": "474686",
      "bag": 3,
      "makespan_200": 62.8,
      "makespan_hi": 62.8,
      "gap_min": 0.0,
      "strat_200": "ortools",
      "strat_hi": "ortools",
      "greedy_200": false,
      "greedy_hi": false,
      "significant": false
    },
    {
      "order_id": "474688",
      "bag": 4,
      "makespan_200": 74.2,
      "makespan_hi": 74.2,
      "gap_min": 0.0,
      "strat_200": "ortools",
      "strat_hi": "ortools",
      "greedy_200": false,
      "greedy_hi": false,
      "significant": false
    },
    {
      "order_id": "474690",
      "bag": 4,
      "makespan_200": 81.1,
      "makespan_hi": 81.1,
      "gap_min": 0.0,
      "strat_200": "ortools",
      "strat_hi": "ortools",
      "greedy_200": false,
      "greedy_hi": false,
      "significant": false
    },
    {
      "order_id": "474692",
      "bag": 3,
      "makespan_200": 63.6,
      "makespan_hi": 63.6,
      "gap_min": 0.0,
      "strat_200": "ortools",
      "strat_hi": "ortools",
      "greedy_200": false,
      "greedy_hi": false,
      "significant": false
    },
    {
      "order_id": "474694",
      "bag": 3,
      "makespan_200": 60.1,
      "makespan_hi": 60.1,
      "gap_min": 0.0,
      "strat_200": "ortools",
      "strat_hi": "ortools",
      "greedy_200": false,
      "greedy_hi": false,
      "significant": false
    },
    {
      "order_id": "474699",
      "bag": 3,
      "makespan_200": 66.0,
      "makespan_hi": 66.0,
      "gap_min": 0.0,
      "strat_200": "ortools",
      "strat_hi": "ortools",
      "greedy_200": false,
      "greedy_hi": false,
      "significant": false
    },
    {
      "order_id": "474703",
      "bag": 4,
      "makespan_200": 49.3,
      "makespan_hi": 49.3,
      "gap_min": 0.0,
      "strat_200": "ortools",
      "strat_hi": "ortools",
      "greedy_200": false,
      "greedy_hi": false,
      "significant": false
    },
    {
      "order_id": "474740",
      "bag": 3,
      "makespan_200": 20044.8,
      "makespan_hi": 20044.8,
      "gap_min": 0.0,
      "strat_200": "greedy_fallback",
      "strat_hi": "greedy_fallback",
      "greedy_200": true,
      "greedy_hi": true,
      "significant": false
    },
    {
      "order_id": "474746",
      "bag": 3,
      "makespan_200": 60.4,
      "makespan_hi": 60.4,
      "gap_min": 0.0,
      "strat_200": "ortools",
      "strat_hi": "ortools",
      "greedy_200": false,
      "greedy_hi": false,
      "significant": false
    },
    {
      "order_id": "474749",
      "bag": 3,
      "makespan_200": 45.4,
      "makespan_hi": 45.4,
      "gap_min": 0.0,
      "strat_200": "ortools",
      "strat_hi": "ortools",
      "greedy_200": false,
      "greedy_hi": false,
      "significant": false
    },
    {
      "order_id": "474752",
      "bag": 3,
      "makespan_200": 55.4,
      "makespan_hi": 55.4,
      "gap_min": 0.0,
      "strat_200": "ortools",
      "strat_hi": "ortools",
      "greedy_200": false,
      "greedy_hi": false,
      "significant": false
    },
    {
      "order_id": "474756",
      "bag": 3,
      "makespan_200": 51.8,
      "makespan_hi": 51.8,
      "gap_min": 0.0,
      "strat_200": "ortools",
      "strat_hi": "ortools",
      "greedy_200": false,
      "greedy_hi": false,
      "significant": false
    },
    {
      "order_id": "474759",
      "bag": 3,
      "makespan_200": 56.3,
      "makespan_hi": 56.3,
      "gap_min": 0.0,
      "strat_200": "ortools",
      "strat_hi": "ortools",
      "greedy_200": false,
      "greedy_hi": false,
      "significant": false
    },
    {
      "order_id": "474761",
      "bag": 4,
      "makespan_200": 78.5,
      "makespan_hi": 78.5,
      "gap_min": 0.0,
      "strat_200": "ortools",
      "strat_hi": "ortools",
      "greedy_200": false,
      "greedy_hi": false,
      "significant": false
    },
    {
      "order_id": "474763",
      "bag": 3,
      "makespan_200": 44.6,
      "makespan_hi": 44.6,
      "gap_min": 0.0,
      "strat_200": "ortools",
      "strat_hi": "ortools",
      "greedy_200": false,
      "greedy_hi": false,
      "significant": false
    },
    {
      "order_id": "474767",
      "bag": 3,
      "makespan_200": 67.6,
      "makespan_hi": 67.6,
      "gap_min": 0.0,
      "strat_200": "ortools",
      "strat_hi": "ortools",
      "greedy_200": false,
      "greedy_hi": false,
      "significant": false
    },
    {
      "order_id": "474769",
      "bag": 3,
      "makespan_200": 53.7,
      "makespan_hi": 53.7,
      "gap_min": 0.0,
      "strat_200": "ortools",
      "strat_hi": "ortools",
      "greedy_200": false,
      "greedy_hi": false,
      "significant": false
    },
    {
      "order_id": "474784",
      "bag": 3,
      "makespan_200": 40040.6,
      "makespan_hi": 40040.6,
      "gap_min": 0.0,
      "strat_200": "greedy_fallback",
      "strat_hi": "greedy_fallback",
      "greedy_200": true,
      "greedy_hi": true,
      "significant": false
    },
    {
      "order_id": "474784",
      "bag": 4,
      "makespan_200": 196.6,
      "makespan_hi": 196.6,
      "gap_min": 0.0,
      "strat_200": "ortools",
      "strat_hi": "ortools",
      "greedy_200": false,
      "greedy_hi": false,
      "significant": false
    },
    {
      "order_id": "474794",
      "bag": 3,
      "makespan_200": 86.0,
      "makespan_hi": 86.0,
      "gap_min": 0.0,
      "strat_200": "ortools",
      "strat_hi": "ortools",
      "greedy_200": false,
      "greedy_hi": false,
      "significant": false
    },
    {
      "order_id": "474784",
      "bag": 3,
      "makespan_200": 20060.2,
      "makespan_hi": 20060.2,
      "gap_min": 0.0,
      "strat_200": "greedy_fallback",
      "strat_hi": "greedy_fallback",
      "greedy_200": true,
      "greedy_hi": true,
      "significant": false
    },
    {
      "order_id": "474801",
      "bag": 3,
      "makespan_200": 20062.4,
      "makespan_hi": 20062.4,
      "gap_min": 0.0,
      "strat_200": "greedy_fallback",
      "strat_hi": "greedy_fallback",
      "greedy_200": true,
      "greedy_hi": true,
      "significant": false
    },
    {
      "order_id": "474784",
      "bag": 3,
      "makespan_200": 112.6,
      "makespan_hi": 112.6,
      "gap_min": 0.0,
      "strat_200": "ortools",
      "strat_hi": "ortools",
      "greedy_200": false,
      "greedy_hi": false,
      "significant": false
    },
    {
      "order_id": "474809",
      "bag": 3,
      "makespan_200": 85.4,
      "makespan_hi": 85.4,
      "gap_min": 0.0,
      "strat_200": "ortools",
      "strat_hi": "ortools",
      "greedy_200": false,
      "greedy_hi": false,
      "significant": false
    },
    {
      "order_id": "474811",
      "bag": 3,
      "makespan_200": 67.2,
      "makespan_hi": 67.2,
      "gap_min": 0.0,
      "strat_200": "ortools",
      "strat_hi": "ortools",
      "greedy_200": false,
      "greedy_hi": false,
      "significant": false
    },
    {
      "order_id": "474812",
      "bag": 4,
      "makespan_200": 61.6,
      "makespan_hi": 61.6,
      "gap_min": 0.0,
      "strat_200": "ortools",
      "strat_hi": "ortools",
      "greedy_200": false,
      "greedy_hi": false,
      "significant": false
    },
    {
      "order_id": "474814",
      "bag": 3,
      "makespan_200": 88.6,
      "makespan_hi": 88.6,
      "gap_min": 0.0,
      "strat_200": "ortools",
      "strat_hi": "ortools",
      "greedy_200": false,
      "greedy_hi": false,
      "significant": false
    },
    {
      "order_id": "474815",
      "bag": 3,
      "makespan_200": 52.0,
      "makespan_hi": 52.0,
      "gap_min": 0.0,
      "strat_200": "ortools",
      "strat_hi": "ortools",
      "greedy_200": false,
      "greedy_hi": false,
      "significant": false
    },
    {
      "order_id": "474818",
      "bag": 5,
      "makespan_200": 75.0,
      "makespan_hi": 75.0,
      "gap_min": 0.0,
      "strat_200": "ortools",
      "strat_hi": "ortools",
      "greedy_200": false,
      "greedy_hi": false,
      "significant": false
    },
    {
      "order_id": "474821",
      "bag": 5,
      "makespan_200": 57.3,
      "makespan_hi": 57.3,
      "gap_min": 0.0,
      "strat_200": "ortools",
      "strat_hi": "ortools",
      "greedy_200": false,
      "greedy_hi": false,
      "significant": false
    },
    {
      "order_id": "474823",
      "bag": 4,
      "makespan_200": 67.0,
      "makespan_hi": 67.0,
      "gap_min": 0.0,
      "strat_200": "ortools",
      "strat_hi": "ortools",
      "greedy_200": false,
      "greedy_hi": false,
      "significant": false
    },
    {
      "order_id": "474825",
      "bag": 4,
      "makespan_200": 109.9,
      "makespan_hi": 109.9,
      "gap_min": 0.0,
      "strat_200": "ortools",
      "strat_hi": "ortools",
      "greedy_200": false,
      "greedy_hi": false,
      "significant": false
    },
    {
      "order_id": "474826",
      "bag": 4,
      "makespan_200": 105.9,
      "makespan_hi": 105.9,
      "gap_min": 0.0,
      "strat_200": "ortools",
      "strat_hi": "ortools",
      "greedy_200": false,
      "greedy_hi": false,
      "significant": false
    },
    {
      "order_id": "474827",
      "bag": 4,
      "makespan_200": 98.2,
      "makespan_hi": 98.2,
      "gap_min": 0.0,
      "strat_200": "ortools",
      "strat_hi": "ortools",
      "greedy_200": false,
      "greedy_hi": false,
      "significant": false
    },
    {
      "order_id": "474829",
      "bag": 3,
      "makespan_200": 65.8,
      "makespan_hi": 65.8,
      "gap_min": 0.0,
      "strat_200": "ortools",
      "strat_hi": "ortools",
      "greedy_200": false,
      "greedy_hi": false,
      "significant": false
    },
    {
      "order_id": "474831",
      "bag": 4,
      "makespan_200": 30053.3,
      "makespan_hi": 30053.3,
      "gap_min": 0.0,
      "strat_200": "greedy_fallback",
      "strat_hi": "greedy_fallback",
      "greedy_200": true,
      "greedy_hi": true,
      "significant": false
    },
    {
      "order_id": "474832",
      "bag": 3,
      "makespan_200": 68.8,
      "makespan_hi": 68.8,
      "gap_min": 0.0,
      "strat_200": "ortools",
      "strat_hi": "ortools",
      "greedy_200": false,
      "greedy_hi": false,
      "significant": false
    },
    {
      "order_id": "474834",
      "bag": 3,
      "makespan_200": 62.6,
      "makespan_hi": 62.6,
      "gap_min": 0.0,
      "strat_200": "ortools",
      "strat_hi": "ortools",
      "greedy_200": false,
      "greedy_hi": false,
      "significant": false
    },
    {
      "order_id": "474836",
      "bag": 4,
      "makespan_200": 79.5,
      "makespan_hi": 79.5,
      "gap_min": 0.0,
      "strat_200": "ortools",
      "strat_hi": "ortools",
      "greedy_200": false,
      "greedy_hi": false,
      "significant": false
    },
    {
      "order_id": "474838",
      "bag": 6,
      "makespan_200": 108.1,
      "makespan_hi": 108.1,
      "gap_min": 0.0,
      "strat_200": "ortools",
      "strat_hi": "ortools",
      "greedy_200": false,
      "greedy_hi": false,
      "significant": false
    },
    {
      "order_id": "474840",
      "bag": 6,
      "makespan_200": 96.3,
      "makespan_hi": 96.3,
      "gap_min": 0.0,
      "strat_200": "ortools",
      "strat_hi": "ortools",
      "greedy_200": false,
      "greedy_hi": false,
      "significant": false
    },
    {
      "order_id": "474842",
      "bag": 3,
      "makespan_200": 80.1,
      "makespan_hi": 80.1,
      "gap_min": 0.0,
      "strat_200": "ortools",
      "strat_hi": "ortools",
      "greedy_200": false,
      "greedy_hi": false,
      "significant": false
    },
    {
      "order_id": "474844",
      "bag": 3,
      "makespan_200": 68.3,
      "makespan_hi": 68.3,
      "gap_min": 0.0,
      "strat_200": "ortools",
      "strat_hi": "ortools",
      "greedy_200": false,
      "greedy_hi": false,
      "significant": false
    },
    {
      "order_id": "474845",
      "bag": 4,
      "makespan_200": 61.1,
      "makespan_hi": 61.1,
      "gap_min": 0.0,
      "strat_200": "ortools",
      "strat_hi": "ortools",
      "greedy_200": false,
      "greedy_hi": false,
      "significant": false
    },
    {
      "order_id": "474846",
      "bag": 3,
      "makespan_200": 111.0,
      "makespan_hi": 98.2,
      "gap_min": 12.8,
      "strat_200": "ortools",
      "strat_hi": "ortools",
      "greedy_200": false,
      "greedy_hi": false,
      "significant": true
    },
    {
      "order_id": "474847",
      "bag": 3,
      "makespan_200": 84.3,
      "makespan_hi": 84.3,
      "gap_min": 0.0,
      "strat_200": "ortools",
      "strat_hi": "ortools",
      "greedy_200": false,
      "greedy_hi": false,
      "significant": false
    },
    {
      "order_id": "474848",
      "bag": 5,
      "makespan_200": 62.4,
      "makespan_hi": 62.4,
      "gap_min": 0.0,
      "strat_200": "ortools",
      "strat_hi": "ortools",
      "greedy_200": false,
      "greedy_hi": false,
      "significant": false
    },
    {
      "order_id": "474850",
      "bag": 5,
      "makespan_200": 63.8,
      "makespan_hi": 63.8,
      "gap_min": 0.0,
      "strat_200": "ortools",
      "strat_hi": "ortools",
      "greedy_200": false,
      "greedy_hi": false,
      "significant": false
    },
    {
      "order_id": "474851",
      "bag": 3,
      "makespan_200": 76.3,
      "makespan_hi": 76.3,
      "gap_min": 0.0,
      "strat_200": "ortools",
      "strat_hi": "ortools",
      "greedy_200": false,
      "greedy_hi": false,
      "significant": false
    },
    {
      "order_id": "474853",
      "bag": 4,
      "makespan_200": 79.1,
      "makespan_hi": 79.1,
      "gap_min": 0.0,
      "strat_200": "ortools",
      "strat_hi": "ortools",
      "greedy_200": false,
      "greedy_hi": false,
      "significant": false
    },
    {
      "order_id": "474854",
      "bag": 4,
      "makespan_200": 82.3,
      "makespan_hi": 82.3,
      "gap_min": 0.0,
      "strat_200": "ortools",
      "strat_hi": "ortools",
      "greedy_200": false,
      "greedy_hi": false,
      "significant": false
    },
    {
      "order_id": "474858",
      "bag": 3,
      "makespan_200": 57.6,
      "makespan_hi": 57.6,
      "gap_min": 0.0,
      "strat_200": "ortools",
      "strat_hi": "ortools",
      "greedy_200": false,
      "greedy_hi": false,
      "significant": false
    },
    {
      "order_id": "474859",
      "bag": 4,
      "makespan_200": 75.2,
      "makespan_hi": 75.2,
      "gap_min": 0.0,
      "strat_200": "ortools",
      "strat_hi": "ortools",
      "greedy_200": false,
      "greedy_hi": false,
      "significant": false
    },
    {
      "order_id": "474861",
      "bag": 3,
      "makespan_200": 55.0,
      "makespan_hi": 55.0,
      "gap_min": 0.0,
      "strat_200": "ortools",
      "strat_hi": "ortools",
      "greedy_200": false,
      "greedy_hi": false,
      "significant": false
    },
    {
      "order_id": "474862",
      "bag": 3,
      "makespan_200": 66.5,
      "makespan_hi": 66.5,
      "gap_min": 0.0,
      "strat_200": "ortools",
      "strat_hi": "ortools",
      "greedy_200": false,
      "greedy_hi": false,
      "significant": false
    },
    {
      "order_id": "474863",
      "bag": 4,
      "makespan_200": 76.6,
      "makespan_hi": 76.6,
      "gap_min": 0.0,
      "strat_200": "ortools",
      "strat_hi": "ortools",
      "greedy_200": false,
      "greedy_hi": false,
      "significant": false
    },
    {
      "order_id": "474864",
      "bag": 4,
      "makespan_200": 75.7,
      "makespan_hi": 75.7,
      "gap_min": 0.0,
      "strat_200": "ortools",
      "strat_hi": "ortools",
      "greedy_200": false,
      "greedy_hi": false,
      "significant": false
    },
    {
      "order_id": "474865",
      "bag": 3,
      "makespan_200": 55.3,
      "makespan_hi": 55.3,
      "gap_min": 0.0,
      "strat_200": "ortools",
      "strat_hi": "ortools",
      "greedy_200": false,
      "greedy_hi": false,
      "significant": false
    },
    {
      "order_id": "474868",
      "bag": 3,
      "makespan_200": 20046.6,
      "makespan_hi": 20046.6,
      "gap_min": 0.0,
      "strat_200": "greedy_fallback",
      "strat_hi": "greedy_fallback",
      "greedy_200": true,
      "greedy_hi": true,
      "significant": false
    },
    {
      "order_id": "474870",
      "bag": 4,
      "makespan_200": 64.6,
      "makespan_hi": 64.6,
      "gap_min": 0.0,
      "strat_200": "ortools",
      "strat_hi": "ortools",
      "greedy_200": false,
      "greedy_hi": false,
      "significant": false
    },
    {
      "order_id": "474873",
      "bag": 3,
      "makespan_200": 52.4,
      "makespan_hi": 52.4,
      "gap_min": 0.0,
      "strat_200": "ortools",
      "strat_hi": "ortools",
      "greedy_200": false,
      "greedy_hi": false,
      "significant": false
    },
    {
      "order_id": "474875",
      "bag": 3,
      "makespan_200": 39.7,
      "makespan_hi": 39.7,
      "gap_min": 0.0,
      "strat_200": "ortools",
      "strat_hi": "ortools",
      "greedy_200": false,
      "greedy_hi": false,
      "significant": false
    },
    {
      "order_id": "474880",
      "bag": 4,
      "makespan_200": 94.5,
      "makespan_hi": 94.5,
      "gap_min": 0.0,
      "strat_200": "ortools",
      "strat_hi": "ortools",
      "greedy_200": false,
      "greedy_hi": false,
      "significant": false
    },
    {
      "order_id": "474884",
      "bag": 3,
      "makespan_200": 73.5,
      "makespan_hi": 73.5,
      "gap_min": 0.0,
      "strat_200": "ortools",
      "strat_hi": "ortools",
      "greedy_200": false,
      "greedy_hi": false,
      "significant": false
    },
    {
      "order_id": "474886",
      "bag": 3,
      "makespan_200": 55.7,
      "makespan_hi": 55.7,
      "gap_min": 0.0,
      "strat_200": "ortools",
      "strat_hi": "ortools",
      "greedy_200": false,
      "greedy_hi": false,
      "significant": false
    },
    {
      "order_id": "474888",
      "bag": 3,
      "makespan_200": 72.1,
      "makespan_hi": 72.1,
      "gap_min": 0.0,
      "strat_200": "ortools",
      "strat_hi": "ortools",
      "greedy_200": false,
      "greedy_hi": false,
      "significant": false
    },
    {
      "order_id": "474893",
      "bag": 3,
      "makespan_200": 79.1,
      "makespan_hi": 79.1,
      "gap_min": 0.0,
      "strat_200": "ortools",
      "strat_hi": "ortools",
      "greedy_200": false,
      "greedy_hi": false,
      "significant": false
    },
    {
      "order_id": "474898",
      "bag": 3,
      "makespan_200": 58.1,
      "makespan_hi": 58.1,
      "gap_min": 0.0,
      "strat_200": "ortools",
      "strat_hi": "ortools",
      "greedy_200": false,
      "greedy_hi": false,
      "significant": false
    },
    {
      "order_id": "474910",
      "bag": 3,
      "makespan_200": 61.9,
      "makespan_hi": 61.9,
      "gap_min": 0.0,
      "strat_200": "ortools",
      "strat_hi": "ortools",
      "greedy_200": false,
      "greedy_hi": false,
      "significant": false
    },
    {
      "order_id": "474922",
      "bag": 3,
      "makespan_200": 68.3,
      "makespan_hi": 76.0,
      "gap_min": -7.7,
      "strat_200": "ortools",
      "strat_hi": "ortools",
      "greedy_200": false,
      "greedy_hi": false,
      "significant": false
    },
    {
      "order_id": "474927",
      "bag": 3,
      "makespan_200": 62.1,
      "makespan_hi": 62.1,
      "gap_min": 0.0,
      "strat_200": "ortools",
      "strat_hi": "ortools",
      "greedy_200": false,
      "greedy_hi": false,
      "significant": false
    },
    {
      "order_id": "474933",
      "bag": 3,
      "makespan_200": 46.8,
      "makespan_hi": 46.8,
      "gap_min": 0.0,
      "strat_200": "ortools",
      "strat_hi": "ortools",
      "greedy_200": false,
      "greedy_hi": false,
      "significant": false
    },
    {
      "order_id": "474942",
      "bag": 3,
      "makespan_200": 63.5,
      "makespan_hi": 63.5,
      "gap_min": 0.0,
      "strat_200": "ortools",
      "strat_hi": "ortools",
      "greedy_200": false,
      "greedy_hi": false,
      "significant": false
    }
  ]
}